bebop
