Metadata-Version: 1.0
Name: bebop-server
Version: 0.3.5
Summary: A tool for rapid web development
Home-page: https://github.com/zeekay/bebop
Author: Zach Kelling
Author-email: zeekayy@gmail.com
License: UNKNOWN
Platform: UNKNOWN
